stdflow/__init__.py
stdflow/_modidx.py
stdflow/_nbdev_broken.py
stdflow/args.py
stdflow/config.py
stdflow/dataframe_ext.py
stdflow/environ_manager.py
stdflow/filemetadata.py
stdflow/pipeline.py
stdflow/step.py
stdflow/step_runner.py
stdflow/stdflow_doc/__init__.py
stdflow/stdflow_doc/documenter.py
stdflow/stdflow_loaders/__init__.py
stdflow/stdflow_loaders/csv.py
stdflow/stdflow_path/__init__.py
stdflow/stdflow_path/data_path.py
stdflow/stdflow_path/path.py
stdflow/stdflow_path/process_path.py
stdflow/stdflow_tree/__init__.py
stdflow/stdflow_tree/tree.py
stdflow/stdflow_types/__init__.py
stdflow/stdflow_types/strftime_type.py
stdflow/stdflow_utils/__init__.py
stdflow/stdflow_utils/bt_print.py
stdflow/stdflow_utils/caller_metadata.py
stdflow/stdflow_utils/execution.py
stdflow/stdflow_utils/io.py
stdflow/stdflow_utils/kernel.py
stdflow/stdflow_utils/list_op.py
stdflow/stdflow_utils/listing.py
stdflow/stdflow_utils/uuid_utils.py
stdflow/stdflow_viz/__init__.py
tests/__init__.py
tests/test_file_name_auto.py
tests/test_multiple_sheets.py
tests/test_multiple_steps.py
tests/test_utils.py
tests/execution/__init__.py
tests/execution/env_export_function.py
tests/execution/env_export_script.py
tests/execution/test_exec.py
tests/old/__init__.py
tests/old/test_load.py
tests/old/test_package_level.py
tests/old/test_package_vesion.py
tests/old/test_save.py
tests/old/test_src.py
tests/old/test_utils.py
tests/old/test_version.py
tests/twitter_data_flow/__init__.py
tests/twitter_data_flow/test_generate.py
stdflow-0.0.73.dist-info/LICENSE
stdflow-0.0.73.dist-info/METADATA
stdflow-0.0.73.dist-info/WHEEL
stdflow-0.0.73.dist-info/entry_points.txt
stdflow-0.0.73.dist-info/top_level.txt
stdflow-0.0.73.dist-info/RECORD
