Metadata-Version: 2.1
Name: stdflow
Version: 0.0.73
Summary: Data flow tool that transform your notebooks and python files into pipeline steps by standardizing the data input / output. [for Data science project]
Home-page: https://github.com/CyprienRicque/stdflow
Author: Cyprien Ricque
Author-email: cyprien.ricque@gmail.com
License: Apache Software License 2.0
Keywords: nbdev jupyter notebook python "data science" data flow pipeline
Classifier: Development Status :: 3 - Alpha
Classifier: Intended Audience :: Developers
Classifier: Natural Language :: English
Classifier: Programming Language :: Python :: 3.7
Classifier: Programming Language :: Python :: 3.8
Classifier: Programming Language :: Python :: 3.9
Classifier: Programming Language :: Python :: 3.10
Classifier: License :: OSI Approved :: Apache Software License
Requires-Python: >=3.7
License-File: LICENSE
Requires-Dist: openpyxl (~=3.1.2)
Requires-Dist: ipynbname
Requires-Dist: nbconvert
Requires-Dist: colorama
Requires-Dist: tqdm
Requires-Dist: jupyter-client
Requires-Dist: typing-extensions (>=4.7.1) ; python_version < "3.8"
Requires-Dist: pandas (~=1.3.5) ; python_version < "3.8"
Requires-Dist: pandas (>=2.0.0) ; python_version >= "3.9"
Provides-Extra: dev
